logstash_filter_run.py
logstash_filter_test.py
logstash_filter_test-0.1.1.data/scripts/logstash_filter_test.py
logstash_filter_test-0.1.1.dist-info/METADATA
logstash_filter_test-0.1.1.dist-info/RECORD
logstash_filter_test-0.1.1.dist-info/WHEEL
logstash_filter_test-0.1.1.dist-info/top_level.txt
