Metadata-Version: 2.1
Name: logstash-filter-test
Version: 0.1.1
Summary: Easily test logstash filter
Home-page: https://github.com/noamraph/logstash-filter-test
Author: Noam Yorav-Raphael
Author-email: noamraph@gmail.com
License: MIT
Platform: UNKNOWN
